{
    "tokenColors": "./metaleapDark.tmTheme",
    "colors": {
        "dropdown.background": "#2d2322",
        "dropdown.border": "#5d5352",
        "dropdown.foreground": "#ada3a2",
        "dropdown.listBackground": "#2d2322",
        "textLink.foreground": "#8fafcf",
        "textLink.activeForeground": "#D09858",
        "button.background": "#507090",
        "button.hoverBackground": "#785838",
        "button.foreground": "#ede3e2",
        "settings.headerForeground": "#cdc3c2",
        "focusBorder": "#987858",
        "breadcrumb.activeSelectionForeground": "#D09858",
        "breadcrumb.focusForeground": "#D09858",
        "breadcrumb.foreground": "#ada3a2",
        "breadcrumbPicker.background": "#2d2322",
        "pickerGroup.foreground": "#8babcb",
        "activityBar.background": "#000000",
        "editorGroupHeader.noTabsBackground": "#2d2322",
        "editorGroup.emptyBackground": "#2d2322",
        "editorGroupHeader.tabsBackground": "#000000",
        "panel.background": "#3d3332",
        "list.highlightForeground": "#D09858",
        "list.activeSelectionBackground": "#4d4342",
        "list.inactiveSelectionBackground": "#4d4342",
        "notificationCenter.border": "#8d8382",
        "notificationCenterHeader.background": "#583818",
        "notificationCenterHeader.foreground": "#cdc3c2",
        "notificationToast.border": "#D09858",
        "notifications.background": "#8d8382",
        "notifications.border": "#6d6362",
        "notifications.foreground": "#1d1312",
        "panelTitle.activeForeground": "#8babcb",
        "peekViewEditor.background": "#3d3332",
        "peekView.border": "#D09858",
        "peekViewTitle.background": "#3d3332",
        "peekViewResult.background": "#3d3332",
        "peekViewResult.selectionBackground": "#583818",
        "progressBar.background": "#583818",
        "sideBar.background": "#3d3332",
        "sideBarSectionHeader.background": "#583818",
        "statusBar.background": "#000000",
        "statusBar.debuggingBackground": "#4d4342",
        "statusBar.noFolderBackground": "#000000",
        "tab.inactiveBackground": "#2d2322",
        "tab.activeForeground": "#d9d5d0",
        "terminal.background": "#2d2322",
        "terminal.ansiBrightBlack": "#5d5352",
        "terminal.foreground": "#ada3a2",
        "titleBar.activeBackground": "#000000",
        "titleBar.inactiveBackground": "#000000",
        "list.hoverBackground": "#4d4342",
        "list.hoverForeground": "#D09858",
        "list.focusForeground": "#D09858",
        "list.focusBackground": "#4d4342",
        "statusBar.foreground": "#ada3a2",
        "sideBar.foreground": "#ada3a2",
        "foreground": "#ada3a2",
        "editor.background": "#4d4342",
        "editor.foreground": "#b7b3b0",
        "quickInput.background": "#2d2322",
        "quickInputTitle.background": "#3d3332",
        "input.background": "#2d2322",
        "input.border": "#5d5352",
        "input.placeholderForeground": "#7d7372",
        "editorCursor.foreground": "#E09050",
        "editorWhitespace.foreground": "#474340",
        "editorIndentGuide.activeBackground": "#3d3332",
        "editorIndentGuide.background": "#474340",
        "editor.hoverHighlightBackground": "#3d3332",
        "editorLink.foreground": "#8fafcf",
        "editorLink.activeForeground": "#8fafcf",
        "peekViewEditor.matchHighlightBackground": "#804020",
        "peekViewResult.matchHighlightBackground": "#804020",
        "selection.background": "#5b5754",
        "editor.selectionBackground": "#3b3734",
        "editor.lineHighlightBackground": "#4a4140",
        "editor.rangeHighlightBackground": "#3a3130",
        "editor.inactiveSelectionBackground": "#404040",
        "editor.findRangeHighlightBackground": "#3a3130",
        "editor.findMatchHighlightBackground": "#804020",
        "editor.findMatchBackground": "#A04020",
        "editor.selectionHighlightBackground": "#3b3734",
        "editor.wordHighlightBackground": "#3b3734",
        "editor.wordHighlightStrongBackground": "#2d2322",
        "editorSuggestWidget.highlightForeground": "#D09858",
        "editorSuggestWidget.selectedBackground": "#583818",
        "editorSuggestWidget.background": "#3d3332",
        "editorSuggestWidget.border": "#7d7372",
        "editorHoverWidget.background": "#3d3332",
        "editorHoverWidget.statusBarBackground": "#583818",
        "editorHoverWidget.border": "#7d7372"
    },
    "name": "metaleapDark"
}
